setup.cfg
setup.py
qcl/__init__.py
qcl/__main__.py
qcl/application.py
qcl/ccdata_xyz.py
qcl/conformers.py
qcl/figs.py
qcl/find.py
qcl/minima.py
qcl/obconformers.py
qcl/parse.py
qcl/periodictable.py
qcl/qcmatrix.py
qcl/rmsd.py
qcl/stretch.py
qcl/templates.py
qcl/utils.py
qcl/write.py
qcl/zmatrix.py
qcl.egg-info/PKG-INFO
qcl.egg-info/SOURCES.txt
qcl.egg-info/dependency_links.txt
qcl.egg-info/entry_points.txt
qcl.egg-info/top_level.txt
test/test_parse.py
test/test_write.py