Metadata-Version: 1.1
Name: qcl
Version: 0.0.3
Summary: Quantum Chemistry Laboratory
Home-page: https://github.com/ben-albrecht/qcl
Author: Ben Albrecht
Author-email: benalbrecht@pitt.edu
License: MIT
Download-URL: https://github.com/ben-albrecht/qcl/tarball/0.0.3
Keywords: Quantum Chemistry
Platform: UNKNOWN
